setup.py
ebo_distributions/Binomialdistribution.py
ebo_distributions/Gaussiandistribution.py
ebo_distributions/Generaldistribution.py
ebo_distributions/__init__.py
ebo_distributions.egg-info/PKG-INFO
ebo_distributions.egg-info/SOURCES.txt
ebo_distributions.egg-info/dependency_links.txt
ebo_distributions.egg-info/not-zip-safe
ebo_distributions.egg-info/top_level.txt