Metadata-Version: 1.0
Name: ebo-distributions
Version: 0.1
Summary: Gaussian and Binomial distributions
Home-page: UNKNOWN
Author: Robert Ebo Armah-Sekum
Author-email: rarmahse@alumni.cmu.edu
License: UNKNOWN
Platform: UNKNOWN
